<?xml version="1.0" encoding="utf-8"?>


<!DOCTYPE assessment
  PUBLIC "-//Carnegie Mellon University//DTD Inline Assessment 1.0//EN" "http://oli.web.cmu.edu/dtd/oli_inline_assessment_1_0.dtd">
<?xml-stylesheet type="text/css" href="http://oli.web.cmu.edu/authoring/oxy-author/oli_inline_assessment_1_1.css"?>

<assessment id="u3_m3_binomial1_tutor1">
   <title>Tutor</title>
<page>   <content>
      <p>In the following random experiment, decide whether the random variable X is binomial or not.</p>
   </content>
   <question id="q1">
      <body>
         <p>There are 6 members in a family (2 parents and 4 children). Let X be the number of family members who have blue eyes.
         </p>
      </body>
      <multiple_choice shuffle="false">
         <choice value="Res1">binomial</choice>
         <choice value="Res2">not binomial</choice>
      </multiple_choice>
      <part>
         <response match="Res1" score="0">
            <feedback>Incorrect. Let's see why X is not binomial. The random
                  experiment consists of 6 trials (6 family members), where the outcome of interest
                  (success) is having blue eyes. Even though X
                  <?oxy_insert_start author="mmyers" timestamp="20101121T193649-0500"?>represents<?oxy_insert_end?><?oxy_delete author="mmyers" timestamp="20101121T193648-0500" content="counts"?>
                  the number of "successes" among the 6 "trials," X is not binomial<?oxy_insert_start author="mmyers" timestamp="20101121T193610-0500"?>,<?oxy_insert_end?>
                  <?oxy_delete author="mmyers" timestamp="20101121T193613-0500" content="since"?><?oxy_insert_start author="mmyers" timestamp="20101121T193614-0500"?>because<?oxy_insert_end?>
                  eye color is hereditary, and therefore the 6 trials are not independent. Knowing,
                  for example, that the father has blue eyes has an impact on the probability that
                  the children have blue eyes. </feedback>
         </response>
         <response match="Res2" score="10">
            <feedback>Good
                  <?oxy_insert_start author="mmyers" timestamp="20101121T193628-0500"?>j<?oxy_insert_end?><?oxy_delete author="mmyers" timestamp="20101121T193628-0500" content="J"?>ob!
                  The random experiment consists of 6 trials (6 family members), where the outcome
                  of interest (success) is having blue eyes. Even though X
                  <?oxy_insert_start author="mmyers" timestamp="20101121T193658-0500"?>represents<?oxy_insert_end?><?oxy_delete author="mmyers" timestamp="20101121T193656-0500" content="counts"?>
                  the number of "successes" among the 6 "trials," X is not binomial<?oxy_insert_start author="mmyers" timestamp="20101121T193707-0500"?>,<?oxy_insert_end?>
                  <?oxy_delete author="mmyers" timestamp="20101121T193708-0500" content="since"?><?oxy_insert_start author="mmyers" timestamp="20101121T193710-0500"?>because<?oxy_insert_end?>
                  eye color is hereditary, and therefore the 6 trials are not independent. Knowing,
                  for example, that the father has blue eyes has an impact on the probability that
                  the children have blue eyes. X, therefore, is not binomial. </feedback>
         </response>
      </part>
   </question>
</page><page>   <content>
      <p>In the following random experiment, decide whether the random variable X is binomial or not.</p>
   </content>
   <question id="q2">
      <body>
         <p>There are 30 people at a party, 12 of which are males.
               <?oxy_insert_start author="mmyers" timestamp="20101201T105646-0500"?>Out of
               <?oxy_insert_end?><?oxy_delete author="mmyers" timestamp="20101201T105653-0500" content="Five of "?>the
               30 people at the
               party<?oxy_insert_start author="mmyers" timestamp="20101201T105658-0500"?>,
               5<?oxy_insert_end?> are selected at random to participate in a game. Let X be the
               number of females that were selected (out of the 5). </p>
      </body>
      <multiple_choice shuffle="false">
         <choice value="Res1">binomial</choice>
         <choice value="Res2">not binomial</choice>
      </multiple_choice>
      <part>
         <response match="Res1" score="0">
            <feedback>Incorrect. Note that you are sampling 5 subjects out of 30
                  without replacement. Therefore, the 5 "trials" (selections), are not independent.
                  Whether the first selected person is a male or a female has an impact on the
                  second person
                  <?oxy_insert_start author="mmyers" timestamp="20101121T194106-0500"?>selected
                  <?oxy_insert_end?>being a female. Recall that the rule of thumb says, when you are
                  sampling without replacement, you can ignore the dependence problem, as long as
                  the population is at least 10 times as large as the sample size. In this case, the
                  "population" consists of the 30 people in the party, and 5 of them were selected.
                  30 is less than 10<?oxy_insert_start author="mmyers" timestamp="20101121T194005-0500"?>
                  <?oxy_insert_end?>*<?oxy_insert_start author="mmyers" timestamp="20101121T194006-0500"?>
                  <?oxy_insert_end?>5, and therefore the rule of thumb is
                  <?oxy_comment_start author="mmyers" timestamp="20101121T200118-0500" comment="There might be an opportunity here to provide further clarity for students. Consider adding the following phrase to both feedback answers for this question ( after reading it closely to make sure I have the right idea!! ):

&quot;Note that the fact that the number of females and males at the party are not equal has no effect on the answer to this question. We are looking at the probability of &quot;success&quot; of choosing a female particpant, not the probability that a chosen student will be female rather than male, so even though the proportion of female to male party guests is not equal, the chances of choosing a female guest in each trial are the same.&quot;"?>not
                  satisfied.<?oxy_comment_end?>
               </feedback>
         </response>
         <response match="Res2" score="10">
            <feedback>Good
                  <?oxy_insert_start author="mmyers" timestamp="20101121T194029-0500"?>j<?oxy_insert_end?><?oxy_delete author="mmyers" timestamp="20101121T194029-0500" content="J"?>ob!
                  Note that you are sampling 5 subjects out of 30 without replacement. Therefore the
                  5 "trials" (selections) are not independent. Whether the first selected person is
                  a male or a female has an impact on the second person
                  <?oxy_insert_start author="mmyers" timestamp="20101121T194059-0500"?>selected
                  <?oxy_insert_end?>being a female. Recall that the rule of thumb says, when you are
                  sampling without replacement, you can ignore the dependence problem, as long as
                  the population is at least 10 times as large as the sample size. In this case, the
                  "population" consists of the 30 people in the party, and 5 of them were selected.
                  30 is less than 10<?oxy_insert_start author="mmyers" timestamp="20101121T194120-0500"?>
                  <?oxy_insert_end?>*<?oxy_insert_start author="mmyers" timestamp="20101121T194120-0500"?>
                  <?oxy_insert_end?>5, and therefore the rule of thumb is not satisfied. </feedback>
         </response>
      </part>
   </question>
</page><page>   <content>
      <p>In the following random experiment, decide whether the random variable X is binomial or not.</p>
   </content>
   <question id="q3">
      <body>
         <p>It is known that roughly 8% of males have some sort of color vision deficiency (also
               known as
               color<?oxy_insert_start author="mmyers" timestamp="20101121T194404-0500"?>-<?oxy_insert_end?><?oxy_delete author="mmyers" timestamp="20101121T194405-0500" content=" "?>blindness).
               A random sample of
               1<?oxy_insert_start author="mmyers" timestamp="20101121T194344-0500"?>,<?oxy_insert_end?>000
               males was selected. Let X be the number of males out of
               the<?oxy_insert_start author="mmyers" timestamp="20101121T194355-0500"?>
               sample<?oxy_insert_end?><?oxy_delete author="mmyers" timestamp="20101121T194353-0500" content="m"?>
               that are
               color<?oxy_insert_start author="mmyers" timestamp="20101121T194408-0500"?>-<?oxy_insert_end?><?oxy_delete author="mmyers" timestamp="20101121T194408-0500" content=" "?>blind. </p>
      </body>
      <multiple_choice shuffle="false">
         <choice value="Res1">binomial</choice>
         <choice value="Res2">not binomial</choice>
      </multiple_choice>
      <part>
         <response match="Res1" score="10">
            <feedback>Good
                  <?oxy_insert_start author="mmyers" timestamp="20101121T194514-0500"?>j<?oxy_insert_end?><?oxy_delete author="mmyers" timestamp="20101121T194514-0500" content="J"?>ob!
                  This random experiment consists of
                  1<?oxy_insert_start author="mmyers" timestamp="20101121T194519-0500"?>,<?oxy_insert_end?>000
                  trials
                  (1<?oxy_insert_start author="mmyers" timestamp="20101121T194524-0500"?>,<?oxy_insert_end?>000
                  males), all having the same probability of being
                  color<?oxy_insert_start author="mmyers" timestamp="20101121T194534-0500"?>-<?oxy_insert_end?><?oxy_delete author="mmyers" timestamp="20101121T194536-0500" content=" "?>blind
                  ("success"), and X
                  <?oxy_insert_start author="mmyers" timestamp="20101121T194543-0500"?>represents<?oxy_insert_end?><?oxy_delete author="mmyers" timestamp="20101121T194541-0500" content="counts"?>
                  how many of the trials (subjects)
                  ended<?oxy_delete author="mmyers" timestamp="20101121T194559-0500" content=" up"?>
                  in a "success" (are
                  color<?oxy_insert_start author="mmyers" timestamp="20101121T194746-0500"?>-<?oxy_insert_end?><?oxy_delete author="mmyers" timestamp="20101121T194746-0500" content=" "?>blind).
                  Note that even though the selection here is without replacement, we can disregard
                  the dependence problem, and regard the trials as independent, since the population
                  (all males) is more than 10 times the sample size
                  (<?oxy_insert_start author="mmyers" timestamp="20101121T194653-0500"?>10 * 1,000 =
                  <?oxy_insert_end?>10,000). </feedback>
         </response>
         <response match="Res2" score="0">
            <feedback>Incorrect. This random experiment consists of
                  1<?oxy_insert_start author="mmyers" timestamp="20101121T194716-0500"?>,<?oxy_insert_end?>000
                  trials
                  (1<?oxy_insert_start author="mmyers" timestamp="20101121T194718-0500"?>,<?oxy_insert_end?>000
                  males), all having the same probability of being
                  color<?oxy_insert_start author="mmyers" timestamp="20101121T194724-0500"?>-<?oxy_insert_end?><?oxy_delete author="mmyers" timestamp="20101121T194724-0500" content=" "?>blind
                  ("success"), and X
                  <?oxy_insert_start author="mmyers" timestamp="20101121T194730-0500"?>represents<?oxy_insert_end?><?oxy_delete author="mmyers" timestamp="20101121T194728-0500" content="counts"?>
                  how many of the trials (subjects) ended
                  <?oxy_delete author="mmyers" timestamp="20101121T194736-0500" content="up "?>in a
                  "success" (are
                  color<?oxy_insert_start author="mmyers" timestamp="20101121T194750-0500"?>-<?oxy_insert_end?><?oxy_delete author="mmyers" timestamp="20101121T194750-0500" content=" "?>blind).
                  Note that even though the selection here is without replacement, we can disregard
                  the dependence problem, and regard the trials as independent, since the population
                  (all males) is more than 10 times the sample size
                  (<?oxy_insert_start author="mmyers" timestamp="20101121T194830-0500"?>10 * 1,000 =
                  <?oxy_insert_end?>10,000). </feedback>
         </response>
      </part>
   </question>
 </page><page>  <content>
      <p>In the following random experiment, decide whether the random variable X is binomial or not.</p>
   </content>
   <question id="q4">
      <body>
         <p>A
               multiple<?oxy_insert_start author="mmyers" timestamp="20101121T194852-0500"?>-<?oxy_insert_end?><?oxy_delete author="mmyers" timestamp="20101121T194852-0500" content=" "?>choice
               quiz has 15 problems, each with 5 possible answers, only one of which is correct. A
               student who does not attend lectures has no clue, and uses an independent random
               guess to answer each of the problems. The random variable X is the number of
               questions the student got right.</p>
      </body>
      <multiple_choice shuffle="false">
         <choice value="Res1">binomial</choice>
         <choice value="Res2">not binomial</choice>
      </multiple_choice>
      <part>
         <response match="Res1" score="10">
            <feedback>Good
                  <?oxy_insert_start author="mmyers" timestamp="20101121T194919-0500"?>j<?oxy_insert_end?><?oxy_delete author="mmyers" timestamp="20101121T194919-0500" content="J"?>ob!
                  This experiment consists of 15 trials (each quiz question is a trial). Since the
                  student uses an independent random guess to answer each of the
                  <?oxy_insert_start author="mmyers" timestamp="20101121T194937-0500"?>15<?oxy_insert_end?><?oxy_delete author="mmyers" timestamp="20101121T194934-0500" content="fifteen"?>
                  questions, the trials are
                  independent<?oxy_insert_start author="mmyers" timestamp="20101121T194943-0500"?>,<?oxy_insert_end?>
                  and all have the same probability of being correctly answered. X
                  <?oxy_insert_start author="mmyers" timestamp="20101121T195147-0500"?>represents<?oxy_insert_end?><?oxy_delete author="mmyers" timestamp="20101121T195146-0500" content="counts"?>
                  how many of the 15 questions ended
                  <?oxy_delete author="mmyers" timestamp="20101121T195220-0500" content="up "?>in a
                  "success" (were answered correctly).</feedback>
         </response>
         <response match="Res2" score="0">
            <feedback>Incorrect. This experiment consists of 15 trials (each quiz
                  question is a trial). Since the student uses an independent random guess to answer
                  each of the
                  <?oxy_insert_start author="mmyers" timestamp="20101121T195157-0500"?>15<?oxy_insert_end?><?oxy_delete author="mmyers" timestamp="20101121T195155-0500" content="fifteen"?>
                  questions, the trials are
                  independent<?oxy_insert_start author="mmyers" timestamp="20101121T195202-0500"?>,<?oxy_insert_end?>
                  and all have the same probability of being correctly answered. X
                  <?oxy_insert_start author="mmyers" timestamp="20101121T195208-0500"?>represents<?oxy_insert_end?><?oxy_delete author="mmyers" timestamp="20101121T195206-0500" content="counts"?>
                  how many of the 15 questions ended
                  <?oxy_delete author="mmyers" timestamp="20101121T195225-0500" content="up "?>in a
                  "success" (were answered correctly), and therefore X is binomial. </feedback>
         </response>
      </part>
   </question>
 </page>
   <page>
   <question id="q5">
      <body>
         <p>In the
               <?oxy_insert_start author="mmyers" timestamp="20101121T195248-0500"?>previous<?oxy_insert_end?><?oxy_delete author="mmyers" timestamp="20101121T195247-0500" content="last"?>
               question (the one about the
               multiple<?oxy_insert_start author="mmyers" timestamp="20101121T195256-0500"?>-<?oxy_insert_end?><?oxy_delete author="mmyers" timestamp="20101121T195256-0500" content=" "?>choice
               quiz), the random variable X is binomial with parameters: </p>
      </body>
      <multiple_choice shuffle="false">
         <choice value="Res1">n = 1/5, p = 15</choice>
         <choice value="Res2">n = 15, p = 1/2</choice>
         <choice value="Res3">n = 15, p = 1/5</choice>
         <choice value="Res4">n = 15, p = 0</choice>
      </multiple_choice>
      <part>
         <response match="Res1" score="0">
            <feedback>Incorrect. You might be confusing n and p. n is the number of
                  trials and p is the (fixed) probability of success in each trial. Here we have 15
                  trials (15 quiz questions), with
                  <?oxy_insert_start author="mmyers" timestamp="20101121T195455-0500"?>a
                  <?oxy_insert_end?>probability of success (answering the question right)
                  <?oxy_insert_start author="mmyers" timestamp="20101121T195459-0500"?>of<?oxy_insert_end?><?oxy_delete author="mmyers" timestamp="20101121T195458-0500" content="being"?>
                  1/5.</feedback>
         </response>
         <response match="Res2" score="0">
            <feedback>Incorrect. While it is true that n = 15 (each of the quiz
                  questions is a trial), p, the probability of "success" (answering the question
                  correctly) is not 1/2. Since each question has 5 possible answers, only one of
                  which is correct, p<?oxy_insert_start author="mmyers" timestamp="20101121T195414-0500"?>
                  <?oxy_insert_end?>=<?oxy_insert_start author="mmyers" timestamp="20101121T195415-0500"?>
                  <?oxy_insert_end?>1/5.</feedback>
         </response>
         <response match="Res3" score="10">
            <feedback>Good
                  <?oxy_insert_start author="mmyers" timestamp="20101121T195426-0500"?>j<?oxy_insert_end?><?oxy_delete author="mmyers" timestamp="20101121T195425-0500" content="J"?>ob!
                  There are 15 trials (15 quiz questions), all having
                  <?oxy_insert_start author="mmyers" timestamp="20101121T195438-0500"?>a
                  <?oxy_insert_end?>probability of success (guessing correctly)
                  <?oxy_insert_start author="mmyers" timestamp="20101121T195446-0500"?>of<?oxy_insert_end?><?oxy_delete author="mmyers" timestamp="20101121T195445-0500" content="being"?>
                  1/5.</feedback>
         </response>
         <response match="Res4" score="0">
            <feedback>Incorrect. While it is true that n = 15 (each of the quiz
                  questions is a trial), p, the probability of "success" (answering the question
                  correctly) is not 0. Since each question has 5 possible answers, only one of which
                  is correct, p<?oxy_insert_start author="mmyers" timestamp="20101121T195518-0500"?>
                  <?oxy_insert_end?>=<?oxy_insert_start author="mmyers" timestamp="20101121T195518-0500"?>
                  <?oxy_insert_end?>1/5. </feedback>
         </response>
      </part>
   </question>
</page>   
</assessment>
