<?xml version="1.0" encoding="UTF-8"?>
<!DOCTYPE objectives PUBLIC "-//Carnegie Mellon University//DTD Learning Objectives 2.0//EN" "http://oli.web.cmu.edu/dtd/oli_learning_objectives_2_0.dtd"><objectives id="lo_review_synthesis"><title>Review and Synthesis</title><objective id="review_intro_LO" high_mastery="2.5" min_practice="2" medium_mastery="1.5" low_opportunity="false">Explore connections between the Big Ideas of Anatomy &amp; Physiology between systems.</objective><objective id="ident_examp_sf_across_LO" high_mastery="2.5" min_practice="2" medium_mastery="1.5" low_opportunity="false">Identify examples of structure and function in anatomy.</objective><objective id="predict_disfunction_structure_LO" high_mastery="2.5" min_practice="2" medium_mastery="1.5" low_opportunity="false">Predict dysfunctions associated with altered anatomical structures.</objective><objective id="ident_size_scale_integration_LO" high_mastery="2.5" min_practice="2" medium_mastery="1.5" low_opportunity="false">Identify how different anatomic size scales integrate for physiological function.</objective><objective id="predict_disfunction_across_scales_LO" high_mastery="2.5" min_practice="2" medium_mastery="1.5" low_opportunity="false">Predict what occurs at length scales if there is dysfunction at another length scale.</objective><objective id="define_identify_aspects_LO" high_mastery="2.5" min_practice="2" medium_mastery="1.5" low_opportunity="false">Define homeostasis, and identify specifics aspects of physiology involving homeostasis.</objective><objective id="complete_loops_LO" high_mastery="2.5" min_practice="2" medium_mastery="1.5" low_opportunity="false">Complete homeostasis loops associated with physiology.</objective><objective id="predict_dysfunction_homeo_LO" high_mastery="2.5" min_practice="2" medium_mastery="1.5" low_opportunity="false">Predict dysfunctions associated with misregulation of homeostasis. </objective><objective id="ident_examples_system_integration_LO" high_mastery="2.5" min_practice="2" medium_mastery="1.5" low_opportunity="false">Identify examples of integrated systems.</objective><objective id="predict_dysfunction_across_systems_LO" high_mastery="2.5" min_practice="2" medium_mastery="1.5" low_opportunity="false">Predict how dysfunction observed in one organ system could reflect dysfunction in other systems.</objective><objective_skills idref="complete_loops_LO"><skillref idref="_u3_list_SKILL" /><skillref idref="complete_loops_SKILL" /></objective_skills><objective_skills idref="define_identify_aspects_LO"><skillref idref="_u3_define_homeostasis_SKILL" /></objective_skills><objective_skills idref="ident_examp_sf_across_LO"><skillref idref="ident_examp_sf_across_SKILL" /></objective_skills><objective_skills idref="ident_examples_system_integration_LO"><skillref idref="ident_examples_system_integration_SKILL" /><skillref idref="_u3_explain_SKILL" /></objective_skills><objective_skills idref="ident_size_scale_integration_LO"><skillref idref="describe_list_order_levels_SKILL" /><skillref idref="ident_size_scale_integration_SKILL" /><skillref idref="describe_levels_SKILL" /></objective_skills><objective_skills idref="predict_disfunction_across_scales_LO"><skillref idref="ident_size_scale_integration_SKILL" /><skillref idref="predict_disfunction_across_scales_SKILL" /></objective_skills><objective_skills idref="predict_disfunction_structure_LO"><skillref idref="predict_disfunction_structure_SKILL" /></objective_skills><objective_skills idref="predict_dysfunction_across_systems_LO"><skillref idref="predict_dysfunction_across_systems_SKILL" /></objective_skills><objective_skills idref="predict_dysfunction_homeo_LO"><skillref idref="_u3_homeo_abnormalities_SKILL" /><skillref idref="_u3_predict_SKILL" /></objective_skills><objective_skills idref="review_intro_LO"><skillref idref="review_intro_SKILL" /></objective_skills></objectives>
