<?xml version="1.0" encoding="UTF-8"?>
<!DOCTYPE assessment PUBLIC "-//Carnegie Mellon University//DTD Inline Assessment MathML 1.4//EN" "http://oli.cmu.edu/dtd/oli_inline_assessment_mathml_1_4.dtd"><assessment xmlns:cmd="http://oli.web.cmu.edu/content/metadata/2.1/" id="identify_three_kinds_cells_myocardium_digt_02"><title>tutor</title><page><question id="q1"><body>Which of the following is correct?</body><multiple_choice shuffle="false"><choice value="choice1">Cardiac muscle cells rely on external calcium to create action potentials.</choice><choice value="choice2">Skeletal muscle cells rely on external calcium to create action potentials.</choice><choice value="choice3">Neural cells rely on external calcium to create action potentials.</choice><choice value="choice4">None of these answers are correct.</choice></multiple_choice><part id="q1_p1"><skillref idref="contrast_action_potentials_cardiac_skeletal_cells_SKILL" /><response match="choice1" score="10"><feedback>Correct. One significant difference between the depolarization of cardiac muscle cells and other cells is their dependence on external calcium.</feedback></response><response match="choice2" score="0"><feedback>Incorrect. Skeletal muscle cells rely on sodium to create action potentials not calcium.</feedback></response><response match="choice3" score="0"><feedback>Incorrect. Neural cells rely on sodium to create action potentials not calcium.</feedback></response><response match="choice4" score="0"><feedback>Incorrect. Skeletal muscle and neural cells rely on sodium to create action potentials, but cardiac muscle relies on external calcium.</feedback></response></part></question></page></assessment>
