<?xml version="1.0" encoding="UTF-8"?>
<!DOCTYPE assessment PUBLIC "-//Carnegie Mellon University//DTD Inline Assessment MathML 1.4//EN" "http://oli.cmu.edu/dtd/oli_inline_assessment_mathml_1_4.dtd"><assessment xmlns:cmd="http://oli.web.cmu.edu/content/metadata/2.1/" id="identify_erythrocytes_leukocytes_thrombocytes_lbd_02"><title>tutor</title><page><question id="q1"><body>Which cell type would typically be the smallest?</body><multiple_choice shuffle="true"><choice value="choice1">red blood cell</choice><choice value="choice2">white blood cell</choice><choice value="choice3">platelet</choice></multiple_choice><part id="q1_p1"><skillref idref="identify_micro_erythrocytes_leukocytes_thrombocytes_SKILL" /><response match="choice1" score="0"><feedback>Incorrect. A red blood cell tends to be 6-9 micrometers in diameter.</feedback></response><response match="choice2" score="0"><feedback>Incorrect. The diameter of a white blood cell ranges from 9-20 micrometers, depending on the type.</feedback></response><response match="choice3" score="10"><feedback>Correct. Platelets are smaller than the other cells. Normal platelets tend to be 2-3 micrometers in diameter.</feedback></response><hint>Consider the basic physical characteristics of each cell type.</hint></part></question></page></assessment>
