<?xml version="1.0" encoding="UTF-8"?>
<!DOCTYPE assessment PUBLIC "-//Carnegie Mellon University//DTD Inline Assessment MathML 1.4//EN" "http://oli.cmu.edu/dtd/oli_inline_assessment_mathml_1_4.dtd"><assessment xmlns:cmd="http://oli.web.cmu.edu/content/metadata/2.1/" id="_u5_m4_skel_integrate_inline01"><title>Integration of Systems</title><page><question id="I_u5_m4_quest01_arthritis"><body><p>How do you think common treatments for rheumatoid arthritis affect the rest of the body? </p></body><multiple_choice id="ans01" shuffle="true"><choice value="pain">Pain in the joints</choice><choice value="infection">Increased susceptibility to infection </choice><choice value="broken_bones">Increased risk of broken bones </choice><choice value="lupus">Lupus, an autoimmune disorder, may be caused </choice></multiple_choice><part id="ffde69e7c1594304b0cfd220ca65fc92"><skillref idref="skeletal_integrate_SKILL" /><response match="infection" score="1"><feedback>Correct. Rheumatoid arthritis (RA) involves the body&apos;s own immune system attacking stressed cartilage. Thus, to treat RA, the immune system must be suppressed. With a weakened immune system, there is an increased risk of infection. </feedback></response><response match="pain" score="0"><feedback>Incorrect. Treatments for rheumatoid arthritis (RA) usually try to reduce the symptom of joint pain.</feedback></response><response match="broken_bones" score="0"><feedback>Incorrect. Some hormonal therapies for rheumatoid arthritis (RA) can increase the risk of certain types of fracture, but generally this is not an issue.</feedback></response><response match="lupus" score="0"><feedback>Incorrect. Lupus is another autoimmune disorder, and many times rheumatoid arthritis (RA) and lupus are treated the same way.</feedback></response><hint>Treatments for autoimmune diseases reduce production of the immune cells that attack healthy tissue.</hint></part></question></page></assessment>
