<?xml version="1.0" encoding="UTF-8"?>      <item ident="questionid" title="_u4_m3_digtutor1a">        <presentation>          <material><mattext texttype="text/plain">What is the sample space S in this case? In other words, what are all the possible outcomes in this case? (Use B for a boy and G for a girl).</mattext></material>          <response_str ident="Short answer 1">            <render_fib fibtype="String" prompt="Box">              <response_label ident="Res 1"/></render_fib></response_str></presentation>        <resprocessing>          <outcomes/>          <respcondition>            <conditionvar>              <other/></conditionvar>            <displayfeedback linkrefid="Feedback always"/></respcondition></resprocessing>        <itemfeedback ident="solution">          <solution>          <solutionmaterial>          <material>            <mattext texttype="text/plain">There are four possible outcomes in this case:B - the first child is a boy, and the couple stops having children.GB - the first child is a girl and the second is a boy, and then the couple stops having children.GGB - the first and second child is a girl and the third is a boy, and the couple stops having children.GGG - all three children are girls but the couple stops having children for financial reasons.			</mattext></material>          </solutionmaterial>          </solution></itemfeedback></item>