<?xml version="1.0" encoding="UTF-8"?>
<!DOCTYPE assessment PUBLIC "-//Carnegie Mellon University//DTD Inline Assessment MathML 1.4//EN" "http://oli.cmu.edu/dtd/oli_inline_assessment_mathml_1_4.dtd"><assessment xmlns:cmd="http://oli.web.cmu.edu/content/metadata/2.1/" id="endo_pit_hypo_digt"><title>tutor</title><page><question id="q1"><body>Which of the following accurately describes the function of the hypothalamus?</body><multiple_choice select="single" shuffle="true"><choice value="A">It is a link between the nervous system and the endocrine system.</choice><choice value="B">It is regulated by the pituitary gland.</choice><choice value="C">It directly regulates all endocrine secretions.</choice><choice value="D">It is responsible for only stimulating the pituitary gland.</choice></multiple_choice><part id="d3300863d17648a8b6f8311f708aaf0f"><skillref idref="endo_pit_hypo_SKILL" /><response match="A" score="10"><feedback>Correct. The hypothalamus has both nervous system and endocrine functions and is a link between them.</feedback></response><response match="B" score="0"><feedback>Incorrect. The hypothalamus can respond to a negative feedback loop but it is not directly controlled by the pituitary gland.</feedback></response><response match="C" score="0"><feedback>Incorrect. The hypothalamus does not directly control all endocrine secretions, it does regulate the pituitary gland which regulates many other glands.</feedback></response><response match="D" score="0"><feedback>Incorrect. The hypothalamus secretes both releasing and inhibiting hormones.</feedback></response></part></question></page></assessment>
